strtovar/__init__.py
strtovar/main.py
strtovar-0.1.1.dist-info/METADATA
strtovar-0.1.1.dist-info/WHEEL
strtovar-0.1.1.dist-info/top_level.txt
strtovar-0.1.1.dist-info/RECORD
